aliyunsdksas/__init__.py
aliyunsdksas/endpoint.py
aliyunsdksas/request/__init__.py
aliyunsdksas/request/v20181203/AddAssetSelectionCriteriaRequest.py
aliyunsdksas/request/v20181203/AddCheckInstanceResultWhiteListRequest.py
aliyunsdksas/request/v20181203/AddCheckResultWhiteListRequest.py
aliyunsdksas/request/v20181203/AddClientUserDefineRuleRequest.py
aliyunsdksas/request/v20181203/AddImageVulWhiteListRequest.py
aliyunsdksas/request/v20181203/AddInstallCodeRequest.py
aliyunsdksas/request/v20181203/AddPrivateRegistryRequest.py
aliyunsdksas/request/v20181203/AddTagWithUuidRequest.py
aliyunsdksas/request/v20181203/AddUninstallClientsByUuidsRequest.py
aliyunsdksas/request/v20181203/AddVpcHoneyPotRequest.py
aliyunsdksas/request/v20181203/AdvanceSecurityEventOperationsRequest.py
aliyunsdksas/request/v20181203/BatchOperateCommonOverallConfigRequest.py
aliyunsdksas/request/v20181203/BindAuthToMachineRequest.py
aliyunsdksas/request/v20181203/CancelOnceTaskRequest.py
aliyunsdksas/request/v20181203/ChangeAssetRefreshTaskConfigRequest.py
aliyunsdksas/request/v20181203/ChangeCheckConfigRequest.py
aliyunsdksas/request/v20181203/ChangeCheckCustomConfigRequest.py
aliyunsdksas/request/v20181203/ChangeSecurityScoreRuleRequest.py
aliyunsdksas/request/v20181203/ChangeUserLangRequest.py
aliyunsdksas/request/v20181203/CheckQuaraFileIdRequest.py
aliyunsdksas/request/v20181203/CheckSecurityEventIdRequest.py
aliyunsdksas/request/v20181203/CheckUserHasEcsRequest.py
aliyunsdksas/request/v20181203/ConfirmVirusEventsRequest.py
aliyunsdksas/request/v20181203/CreateAgentlessScanTaskRequest.py
aliyunsdksas/request/v20181203/CreateAntiBruteForceRuleRequest.py
aliyunsdksas/request/v20181203/CreateAssetSelectionConfigRequest.py
aliyunsdksas/request/v20181203/CreateBackupPolicyRequest.py
aliyunsdksas/request/v20181203/CreateContainerScanTaskByAppNameRequest.py
aliyunsdksas/request/v20181203/CreateContainerScanTaskRequest.py
aliyunsdksas/request/v20181203/CreateCustomBlockRecordRequest.py
aliyun_python_sdk_sas-2.0.3.dist-info/LICENSE
aliyun_python_sdk_sas-2.0.3.dist-info/METADATA
aliyun_python_sdk_sas-2.0.3.dist-info/WHEEL
aliyun_python_sdk_sas-2.0.3.dist-info/top_level.txt
aliyun_python_sdk_sas-2.0.3.dist-info/RECORD
